bridge_utils/__init__.py
bridge_utils/update4suit.py
bridge_utils/zyj2convert.py
bridge_utils/deallog/Bids.png
bridge_utils/deallog/BoxBid.png
bridge_utils/deallog/BoxPlay.png
bridge_utils/deallog/BridgeBase.js
bridge_utils/deallog/BridgeUtil.js
bridge_utils/deallog/ButL.png
bridge_utils/deallog/ButR.png
bridge_utils/deallog/CardBack.png
bridge_utils/deallog/Cards.png
bridge_utils/deallog/DealLog.html
bridge_utils/deallog/DealLog.js
bridge_utils/deallog/README.md
bridge_utils/deallog/Request.js
bridge_utils/deallog/cocos2d-js-v3.6-lite.js
bridge_utils/deallog/index.html
bridge_utils/deallog/project.json
bridge_utils/mdbridge/__init__.py
bridge_utils/mdbridge/index.md
bridge_utils/mdbridge/lin2pbn.py
bridge_utils/mdbridge/mdbridge2html.py
bridge_utils/mdbridge/mdbridge2latex.py
bridge_utils/mdbridge/meta.txt
bridge_utils/mdbridge/ramsey.md
bridge_utils/pbn2html/__init__.py
bridge_utils/pbn2html/all_template.html
bridge_utils/pbn2html/auction_template.html
bridge_utils/pbn2html/deal_template.html
bridge_utils/pbn2html/game_state.py
bridge_utils/pbn2html/pbn2html.py
bridge_utils/pbn2html/pbn_parser.py
bridge_utils/pbn2html/template.html
bridge_utils/xin2pbn/__init__.py
bridge_utils/xin2pbn/demo.pbn
bridge_utils/xin2pbn/lin2pbn.py
bridge_utils/xin2pbn/output.pbn
bridge_utils/xin2pbn/template.html
bridge_utils/xin2pbn/template.pbn
bridge_utils/xin2pbn/xin2pbn.py
bridge_utils/xin2pbn/deallog/Bids.png
bridge_utils/xin2pbn/deallog/BoxBid.png
bridge_utils/xin2pbn/deallog/BoxPlay.png
bridge_utils/xin2pbn/deallog/BridgeBase.js
bridge_utils/xin2pbn/deallog/BridgeUtil.js
bridge_utils/xin2pbn/deallog/ButL.png
bridge_utils/xin2pbn/deallog/ButR.png
bridge_utils/xin2pbn/deallog/CardBack.png
bridge_utils/xin2pbn/deallog/Cards.png
bridge_utils/xin2pbn/deallog/DealLog.html
bridge_utils/xin2pbn/deallog/DealLog.js
bridge_utils/xin2pbn/deallog/README.md
bridge_utils/xin2pbn/deallog/Request.js
bridge_utils/xin2pbn/deallog/cocos2d-js-v3.6-lite.js
bridge_utils/xin2pbn/deallog/index.html
bridge_utils-0.4.1.dist-info/LICENSE
bridge_utils-0.4.1.dist-info/METADATA
bridge_utils-0.4.1.dist-info/WHEEL
bridge_utils-0.4.1.dist-info/entry_points.txt
bridge_utils-0.4.1.dist-info/top_level.txt
bridge_utils-0.4.1.dist-info/RECORD
