Metadata-Version: 2.1
Name: bridge-utils
Version: 0.4.1
Summary: bridge (contract game) utils for PBN & xinrui & bbo
Home-page: https://gitlab.com/xrgopher/bridge-utils
Author: xrgopher
Author-email: xrgopher@outlook.com
License: UNKNOWN
Platform: UNKNOWN
Classifier: Programming Language :: Python :: 3
Classifier: License :: OSI Approved :: MIT License
Classifier: Operating System :: OS Independent
Requires-Python: >=3.6
License-File: LICENSE
Requires-Dist: requests
Requires-Dist: repackage
Requires-Dist: markdown
